hsi_wizard-0.1.42.dist-info/licenses/LICENSE
wizard/__init__.py
wizard/_core/__init__.py
wizard/_core/datacube.py
wizard/_core/datacube_ops.py
wizard/_exploration/__init__.py
wizard/_exploration/faces.py
wizard/_exploration/plotter.py
wizard/_exploration/surface.py
wizard/_processing/__init__.py
wizard/_processing/cluster.py
wizard/_processing/spectral.py
wizard/_utils/__init__.py
wizard/_utils/decorators.py
wizard/_utils/example.py
wizard/_utils/helper.py
wizard/_utils/tracker.py
wizard/_utils/_loader/__init__.py
wizard/_utils/_loader/_helper.py
wizard/_utils/_loader/csv.py
wizard/_utils/_loader/folder.py
wizard/_utils/_loader/fsm.py
wizard/_utils/_loader/hdr.py
wizard/_utils/_loader/image.py
wizard/_utils/_loader/nrrd.py
wizard/_utils/_loader/pickle.py
wizard/_utils/_loader/tdms.py
wizard/_utils/_loader/xlsx.py
hsi_wizard-0.1.42.dist-info/METADATA
hsi_wizard-0.1.42.dist-info/WHEEL
hsi_wizard-0.1.42.dist-info/top_level.txt
hsi_wizard-0.1.42.dist-info/RECORD
