Metadata-Version: 2.4
Name: hsi-wizard
Version: 0.1.42
Summary: See Beyond the Visible: The Magic of Hyperspectral Imaging
Author-email: Felix Wuehler <f.wuehler@hs-mannheim.de>
Project-URL: Homepage, https://github.com/BlueSpacePotato/hsi-wizard
Project-URL: Issues, https://github.com/BlueSpacePotato/hsi-wizard/issues
Classifier: Programming Language :: Python :: 3
Classifier: License :: OSI Approved :: MIT License
Classifier: Operating System :: OS Independent
Requires-Python: >=3.10
License-File: LICENSE
Requires-Dist: numba
Requires-Dist: numpy
Requires-Dist: matplotlib
Requires-Dist: opencv-python
Requires-Dist: rich
Requires-Dist: nptdms
Requires-Dist: pandas
Requires-Dist: tqdm
Requires-Dist: imageio
Requires-Dist: openpyxl
Requires-Dist: PyYAML
Requires-Dist: joblib
Requires-Dist: scipy
Requires-Dist: pynrrd
Requires-Dist: rembg
Requires-Dist: onnxruntime
Requires-Dist: scikit-learn
Requires-Dist: spectral
Provides-Extra: tests
Requires-Dist: pydocstyle; extra == "tests"
Requires-Dist: flake8; extra == "tests"
Requires-Dist: pytest; extra == "tests"
Requires-Dist: pytest-cov; extra == "tests"
Requires-Dist: pytest-mock; extra == "tests"
Provides-Extra: build
Requires-Dist: twine; extra == "build"
Requires-Dist: build; extra == "build"
Dynamic: license-file
